CHANGES
LICENSE
MANIFEST.in
README.rst
setup.py
ajax_upload/__init__.py
ajax_upload/admin.py
ajax_upload/forms.py
ajax_upload/models.py
ajax_upload/settings.py
ajax_upload/urls.py
ajax_upload/views.py
ajax_upload/widgets.py
ajax_upload/static/ajax_upload/css/ajax-upload-widget.css
ajax_upload/static/ajax_upload/js/ajax-upload-widget.js
ajax_upload/static/ajax_upload/js/jquery.iframe-transport.js
ajax_upload/tests/__init__.py
ajax_upload/tests/forms.py
ajax_upload/tests/tests.py
ajax_upload/tests/urls.py
ajax_upload/tests/views.py
ajax_upload/tests/files/test.png
django_ajax_upload_widget.egg-info/PKG-INFO
django_ajax_upload_widget.egg-info/SOURCES.txt
django_ajax_upload_widget.egg-info/dependency_links.txt
django_ajax_upload_widget.egg-info/not-zip-safe
django_ajax_upload_widget.egg-info/top_level.txt
example/__init__.py
example/forms.py
example/models.py
example/urls.py
example/views.py
example/templates/example/product.html