Metadata-Version: 1.0
Name: django-ajax-upload-widget
Version: 0.5.3
Summary: Provides AJAX file upload functionality for FileFields and ImageFields with a simple widget replacement in the form.
Home-page: http://github.com/zmathew/django-ajax-upload-widget
Author: Zach Mathew
Author-email: UNKNOWN
License: BSD
Platform: UNKNOWN
Classifier: Framework :: Django
Classifier: Intended Audience :: Developers
Classifier: License :: OSI Approved :: BSD License
Classifier: Operating System :: OS Independent
Classifier: Topic :: Software Development
